rtasr/__init__.py
rtasr/__main__.py
rtasr/cli_messages.py
rtasr/concurrency.py
rtasr/constants.py
rtasr/plots.py
rtasr/py.typed
rtasr/speaker_map.py
rtasr/utils.py
rtasr/asr/__init__.py
rtasr/asr/options.py
rtasr/asr/providers.py
rtasr/asr/schemas.py
rtasr/cli/__init__.py
rtasr/cli/audio_length_command.py
rtasr/cli/download_command.py
rtasr/cli/evaluation_command.py
rtasr/cli/list_command.py
rtasr/cli/plot_command.py
rtasr/cli/transcription_command.py
rtasr/datasets/__init__.py
rtasr/datasets/dataset_ami.py
rtasr/datasets/dataset_fleurs.py
rtasr/datasets/dataset_voxconverse.py
rtasr/evaluation/__init__.py
rtasr/evaluation/der.py
rtasr/evaluation/schemas.py
rtasr/evaluation/wer.py
rtasr-0.0.7.dist-info/METADATA
rtasr-0.0.7.dist-info/WHEEL
rtasr-0.0.7.dist-info/entry_points.txt
rtasr-0.0.7.dist-info/licenses/LICENSE
rtasr-0.0.7.dist-info/RECORD
