Metadata-Version: 2.1
Name: rtasr
Version: 0.0.7
Summary: 🏆 Run benchmarks against the most common ASR tools on the market.
Project-URL: Documentation, https://Wordcab.github.io/rtasr
Project-URL: Issues, https://github.com/Wordcab/rtasr/issues
Project-URL: Source, https://github.com/Wordcab/rtasr
Author: Wordcab
License-Expression: MIT
License-File: LICENSE
Classifier: Development Status :: 4 - Beta
Classifier: Intended Audience :: Developers
Classifier: License :: OSI Approved :: MIT License
Classifier: Programming Language :: Python
Classifier: Programming Language :: Python :: 3.8
Classifier: Programming Language :: Python :: 3.9
Classifier: Programming Language :: Python :: 3.10
Classifier: Programming Language :: Python :: 3.11
Classifier: Programming Language :: Python :: Implementation :: CPython
Classifier: Programming Language :: Python :: Implementation :: PyPy
Classifier: Topic :: Internet
Classifier: Topic :: Software Development
Classifier: Topic :: Software Development :: Libraries
Classifier: Topic :: Software Development :: Libraries :: Application Frameworks
Classifier: Topic :: Software Development :: Libraries :: Python Modules
Requires-Python: <3.12,>=3.8
Requires-Dist: aiofiles>=23.2.1
Requires-Dist: aiohttp>=3.8.5
Requires-Dist: aiopath>=0.5.12
Requires-Dist: datasets[audio]>=2.14.4
Requires-Dist: jiwer>=3.0.2
Requires-Dist: pydantic>=2.2.0
Requires-Dist: python-dotenv>=1.0.0
Requires-Dist: rich-argparse>=1.2.0
Requires-Dist: rich>=13.5.2
Requires-Dist: seaborn>=0.12.2
Requires-Dist: spy-der>=0.4.0
Provides-Extra: dev
Requires-Dist: rtasr[docs,quality,tests]; extra == 'dev'
Provides-Extra: docs
Requires-Dist: mkdocs-git-revision-date-localized-plugin~=1.1.0; extra == 'docs'
Requires-Dist: mkdocs-material~=8.5.4; extra == 'docs'
Requires-Dist: mkdocstrings[python]~=0.19.0; extra == 'docs'
Requires-Dist: mkdocs~=1.4.0; extra == 'docs'
Provides-Extra: quality
Requires-Dist: black~=22.10.0; extra == 'quality'
Requires-Dist: pre-commit~=2.20.0; extra == 'quality'
Requires-Dist: ruff~=0.0.263; extra == 'quality'
Provides-Extra: tests
Requires-Dist: pytest-asyncio>=0.21.1; extra == 'tests'
Requires-Dist: pytest-cov>=4.1; extra == 'tests'
Requires-Dist: pytest>=7.1.2; extra == 'tests'
